prismWriter/__init__.py
prismWriter/gui.py
prismWriter/prism_template2.pzfx
prismWriter/prism_template_write_test.pzfx
prismWriter/prism_writer.py
prismWriter/streamlit_app.py
prismWriter/schema/prism5xmlschema.xml
prismWriter/schema/prism5xmlstylesheet.xml
prismwriter-1.0.0.dist-info/LICENSE
prismwriter-1.0.0.dist-info/METADATA
prismwriter-1.0.0.dist-info/WHEEL
prismwriter-1.0.0.dist-info/entry_points.txt
prismwriter-1.0.0.dist-info/top_level.txt
prismwriter-1.0.0.dist-info/RECORD
