Metadata-Version: 2.1
Name: prismWriter
Version: 1.0.0
Summary: Python library for programmatically creating and manipulating GraphPad Prism (.pzfx) files
Author: smestern
License: MIT License
Project-URL: Homepage, https://github.com/smestern/prismWriter
Project-URL: Repository, https://github.com/smestern/prismWriter
Project-URL: Documentation, https://github.com/smestern/prismWriter#readme
Project-URL: Bug Tracker, https://github.com/smestern/prismWriter/issues
Keywords: graphpad,prism,pzfx,data visualization,scientific,pandas
Classifier: Development Status :: 4 - Beta
Classifier: Intended Audience :: Science/Research
Classifier: Intended Audience :: Developers
Classifier: License :: OSI Approved :: MIT License
Classifier: Operating System :: OS Independent
Classifier: Programming Language :: Python :: 3
Classifier: Programming Language :: Python :: 3.8
Classifier: Programming Language :: Python :: 3.9
Classifier: Programming Language :: Python :: 3.10
Classifier: Programming Language :: Python :: 3.11
Classifier: Programming Language :: Python :: 3.12
Classifier: Topic :: Scientific/Engineering
Classifier: Topic :: Scientific/Engineering :: Visualization
Requires-Python: >=3.8
License-File: LICENSE
Requires-Dist: numpy>=1.20
Requires-Dist: pandas>=1.3
Requires-Dist: openpyxl>=3.0
Provides-Extra: all
Requires-Dist: PySide2>=5.15; extra == "all"
Requires-Dist: streamlit>=1.20; extra == "all"
Provides-Extra: dev
Requires-Dist: pytest>=7.0; extra == "dev"
Requires-Dist: pytest-cov; extra == "dev"
Requires-Dist: black; extra == "dev"
Requires-Dist: flake8; extra == "dev"
Requires-Dist: build; extra == "dev"
Requires-Dist: twine; extra == "dev"
Provides-Extra: gui
Requires-Dist: PySide2>=5.15; extra == "gui"
Provides-Extra: web
Requires-Dist: streamlit>=1.20; extra == "web"
